{
  "footer": {
    "blocks": ["footer-layout.desktop", "footer-layout.mobile"]
  },

  "footer-layout.desktop": {
    "children": ["flex-layout.row#footer-1-desktop"]
  },

  "flex-layout.row#footer-1-desktop": {
    "children": [
      "share"
    ],
    "props": {
      "blockClass": "menu-row",
      "paddingTop": 6,
      "paddingBottom": 3,
      "fullWidth": true
    }
  },

  "share": {
    "props": {
      "social": {
        "Facebook": false,
        "Twitter": false,
        "WhatsApp": true,
        "Pinterest": false
      }
    }
  }
}
